{
  "schema_version": 1,
  "date": "2026-07-24",
  "generated_at": "2026-07-24T09:00:43.644577+09:00",
  "model_id": "morning_logit_lane_v1_20260713T215525",
  "races": [
    {
      "venue": {
        "code": "01",
        "name": "桐生"
      },
      "race_no": 1,
      "close_scheduled_at": "2026-07-24T15:28:00+09:00",
      "probs": {
        "1": 0.4034,
        "2": 0.1695,
        "3": 0.1108,
        "4": 0.0364,
        "5": 0.2073,
        "6": 0.0726
      },
      "top_pick": 1,
      "confidence": 0.4034,
      "reason_tags": [
        "1号艇（イン）"
      ]
    },
    {
      "venue": {
        "code": "01",
        "name": "桐生"
      },
      "race_no": 2,
      "close_scheduled_at": "2026-07-24T16:02:00+09:00",
      "probs": {
        "1": 0.2823,
        "2": 0.1516,
        "3": 0.1243,
        "4": 0.2772,
        "5": 0.0226,
        "6": 0.1419
      },
      "top_pick": 1,
      "confidence": 0.2823,
      "reason_tags": [
        "1号艇（イン）"
      ]
    },
    {
      "venue": {
        "code": "01",
        "name": "桐生"
      },
      "race_no": 3,
      "close_scheduled_at": "2026-07-24T16:28:00+09:00",
      "probs": {
        "1": 0.3264,
        "2": 0.3454,
        "3": 0.1559,
        "4": 0.0556,
        "5": 0.0298,
        "6": 0.0869
      },
      "top_pick": 2,
      "confidence": 0.3454,
      "reason_tags": [
        "全国勝率5.74はレース内1位",
        "当地勝率5.89はレース内1位"
      ]
    },
    {
      "venue": {
        "code": "01",
        "name": "桐生"
      },
      "race_no": 4,
      "close_scheduled_at": "2026-07-24T17:00:00+09:00",
      "probs": {
        "1": 0.4079,
        "2": 0.2954,
        "3": 0.0682,
        "4": 0.1357,
        "5": 0.0113,
        "6": 0.0816
      },
      "top_pick": 1,
      "confidence": 0.4079,
      "reason_tags": [
        "1号艇（イン）"
      ]
    },
    {
      "venue": {
        "code": "01",
        "name": "桐生"
      },
      "race_no": 5,
      "close_scheduled_at": "2026-07-24T17:24:00+09:00",
      "probs": {
        "1": 0.2442,
        "2": 0.5377,
        "3": 0.1385,
        "4": 0.0399,
        "5": 0.0193,
        "6": 0.0204
      },
      "top_pick": 2,
      "confidence": 0.5377,
      "reason_tags": [
        "全国勝率7.28はレース内1位",
        "当地勝率7.10はレース内1位"
      ]
    },
    {
      "venue": {
        "code": "01",
        "name": "桐生"
      },
      "race_no": 6,
      "close_scheduled_at": "2026-07-24T17:50:00+09:00",
      "probs": {
        "1": 0.8291,
        "2": 0.0444,
        "3": 0.0305,
        "4": 0.0476,
        "5": 0.032,
        "6": 0.0164
      },
      "top_pick": 1,
      "confidence": 0.8291,
      "reason_tags": [
        "全国勝率6.90はレース内1位",
        "当地勝率7.00はレース内1位"
      ]
    },
    {
      "venue": {
        "code": "01",
        "name": "桐生"
      },
      "race_no": 7,
      "close_scheduled_at": "2026-07-24T18:14:00+09:00",
      "probs": {
        "1": 0.4389,
        "2": 0.0311,
        "3": 0.4301,
        "4": 0.0338,
        "5": 0.0336,
        "6": 0.0325
      },
      "top_pick": 1,
      "confidence": 0.4389,
      "reason_tags": [
        "1号艇（イン）"
      ]
    },
    {
      "venue": {
        "code": "01",
        "name": "桐生"
      },
      "race_no": 8,
      "close_scheduled_at": "2026-07-24T18:40:00+09:00",
      "probs": {
        "1": 0.5393,
        "2": 0.0857,
        "3": 0.0575,
        "4": 0.0605,
        "5": 0.2391,
        "6": 0.018
      },
      "top_pick": 1,
      "confidence": 0.5393,
      "reason_tags": [
        "当地勝率5.90はレース内1位",
        "モーター2連率42%はレース内1位"
      ]
    },
    {
      "venue": {
        "code": "01",
        "name": "桐生"
      },
      "race_no": 9,
      "close_scheduled_at": "2026-07-24T19:09:00+09:00",
      "probs": {
        "1": 0.289,
        "2": 0.1676,
        "3": 0.157,
        "4": 0.2531,
        "5": 0.1212,
        "6": 0.012
      },
      "top_pick": 1,
      "confidence": 0.289,
      "reason_tags": [
        "1号艇（イン）"
      ]
    },
    {
      "venue": {
        "code": "01",
        "name": "桐生"
      },
      "race_no": 10,
      "close_scheduled_at": "2026-07-24T19:36:00+09:00",
      "probs": {
        "1": 0.4253,
        "2": 0.1113,
        "3": 0.0726,
        "4": 0.2583,
        "5": 0.0971,
        "6": 0.0354
      },
      "top_pick": 1,
      "confidence": 0.4253,
      "reason_tags": [
        "1号艇（イン）"
      ]
    },
    {
      "venue": {
        "code": "01",
        "name": "桐生"
      },
      "race_no": 11,
      "close_scheduled_at": "2026-07-24T20:02:00+09:00",
      "probs": {
        "1": 0.7416,
        "2": 0.0468,
        "3": 0.1585,
        "4": 0.0329,
        "5": 0.0076,
        "6": 0.0126
      },
      "top_pick": 1,
      "confidence": 0.7416,
      "reason_tags": [
        "当地勝率7.20はレース内1位",
        "1号艇（イン）"
      ]
    },
    {
      "venue": {
        "code": "01",
        "name": "桐生"
      },
      "race_no": 12,
      "close_scheduled_at": "2026-07-24T20:31:00+09:00",
      "probs": {
        "1": 0.7393,
        "2": 0.1082,
        "3": 0.1168,
        "4": 0.0187,
        "5": 0.0131,
        "6": 0.0039
      },
      "top_pick": 1,
      "confidence": 0.7393,
      "reason_tags": [
        "全国勝率7.28はレース内1位",
        "当地勝率7.10はレース内1位"
      ]
    },
    {
      "venue": {
        "code": "02",
        "name": "戸田"
      },
      "race_no": 1,
      "close_scheduled_at": "2026-07-24T10:47:00+09:00",
      "probs": {
        "1": 0.4608,
        "2": 0.2385,
        "3": 0.1162,
        "4": 0.0924,
        "5": 0.0651,
        "6": 0.027
      },
      "top_pick": 1,
      "confidence": 0.4608,
      "reason_tags": [
        "全国勝率4.88はレース内1位",
        "1号艇（イン）"
      ]
    },
    {
      "venue": {
        "code": "02",
        "name": "戸田"
      },
      "race_no": 2,
      "close_scheduled_at": "2026-07-24T11:16:00+09:00",
      "probs": {
        "1": 0.3922,
        "2": 0.2345,
        "3": 0.083,
        "4": 0.147,
        "5": 0.1205,
        "6": 0.0227
      },
      "top_pick": 1,
      "confidence": 0.3922,
      "reason_tags": [
        "1号艇（イン）"
      ]
    },
    {
      "venue": {
        "code": "02",
        "name": "戸田"
      },
      "race_no": 3,
      "close_scheduled_at": "2026-07-24T11:45:00+09:00",
      "probs": {
        "1": 0.2818,
        "2": 0.201,
        "3": 0.2176,
        "4": 0.0759,
        "5": 0.2083,
        "6": 0.0155
      },
      "top_pick": 1,
      "confidence": 0.2818,
      "reason_tags": [
        "1号艇（イン）"
      ]
    },
    {
      "venue": {
        "code": "02",
        "name": "戸田"
      },
      "race_no": 4,
      "close_scheduled_at": "2026-07-24T12:14:00+09:00",
      "probs": {
        "1": 0.2231,
        "2": 0.3568,
        "3": 0.1014,
        "4": 0.2325,
        "5": 0.0476,
        "6": 0.0387
      },
      "top_pick": 2,
      "confidence": 0.3568,
      "reason_tags": [
        "当地勝率6.86はレース内1位",
        "モーター2連率40%はレース内1位"
      ]
    },
    {
      "venue": {
        "code": "02",
        "name": "戸田"
      },
      "race_no": 5,
      "close_scheduled_at": "2026-07-24T12:44:00+09:00",
      "probs": {
        "1": 0.6444,
        "2": 0.094,
        "3": 0.0487,
        "4": 0.1863,
        "5": 0.0202,
        "6": 0.0064
      },
      "top_pick": 1,
      "confidence": 0.6444,
      "reason_tags": [
        "1号艇（イン）"
      ]
    },
    {
      "venue": {
        "code": "02",
        "name": "戸田"
      },
      "race_no": 6,
      "close_scheduled_at": "2026-07-24T13:14:00+09:00",
      "probs": {
        "1": 0.2248,
        "2": 0.0451,
        "3": 0.4964,
        "4": 0.0782,
        "5": 0.1447,
        "6": 0.0108
      },
      "top_pick": 3,
      "confidence": 0.4964,
      "reason_tags": [
        "全国勝率6.16はレース内1位",
        "当地勝率5.70はレース内1位"
      ]
    },
    {
      "venue": {
        "code": "02",
        "name": "戸田"
      },
      "race_no": 7,
      "close_scheduled_at": "2026-07-24T13:45:00+09:00",
      "probs": {
        "1": 0.8379,
        "2": 0.055,
        "3": 0.0496,
        "4": 0.0471,
        "5": 0.0083,
        "6": 0.002
      },
      "top_pick": 1,
      "confidence": 0.8379,
      "reason_tags": [
        "全国勝率6.94はレース内1位",
        "当地勝率6.46はレース内1位"
      ]
    },
    {
      "venue": {
        "code": "02",
        "name": "戸田"
      },
      "race_no": 8,
      "close_scheduled_at": "2026-07-24T14:16:00+09:00",
      "probs": {
        "1": 0.2522,
        "2": 0.2138,
        "3": 0.123,
        "4": 0.1859,
        "5": 0.0431,
        "6": 0.182
      },
      "top_pick": 1,
      "confidence": 0.2522,
      "reason_tags": [
        "1号艇（イン）"
      ]
    },
    {
      "venue": {
        "code": "02",
        "name": "戸田"
      },
      "race_no": 9,
      "close_scheduled_at": "2026-07-24T14:48:00+09:00",
      "probs": {
        "1": 0.6138,
        "2": 0.0845,
        "3": 0.133,
        "4": 0.0995,
        "5": 0.0604,
        "6": 0.0089
      },
      "top_pick": 1,
      "confidence": 0.6138,
      "reason_tags": [
        "当地勝率6.35はレース内1位",
        "1号艇（イン）"
      ]
    },
    {
      "venue": {
        "code": "02",
        "name": "戸田"
      },
      "race_no": 10,
      "close_scheduled_at": "2026-07-24T15:21:00+09:00",
      "probs": {
        "1": 0.4539,
        "2": 0.0904,
        "3": 0.0843,
        "4": 0.1945,
        "5": 0.1543,
        "6": 0.0227
      },
      "top_pick": 1,
      "confidence": 0.4539,
      "reason_tags": [
        "1号艇（イン）"
      ]
    },
    {
      "venue": {
        "code": "02",
        "name": "戸田"
      },
      "race_no": 11,
      "close_scheduled_at": "2026-07-24T15:55:00+09:00",
      "probs": {
        "1": 0.4459,
        "2": 0.2326,
        "3": 0.196,
        "4": 0.0678,
        "5": 0.0218,
        "6": 0.036
      },
      "top_pick": 1,
      "confidence": 0.4459,
      "reason_tags": [
        "レース内で唯一のA1級",
        "1号艇（イン）"
      ]
    },
    {
      "venue": {
        "code": "02",
        "name": "戸田"
      },
      "race_no": 12,
      "close_scheduled_at": "2026-07-24T16:30:00+09:00",
      "probs": {
        "1": 0.4298,
        "2": 0.1658,
        "3": 0.1514,
        "4": 0.1846,
        "5": 0.0464,
        "6": 0.0221
      },
      "top_pick": 1,
      "confidence": 0.4298,
      "reason_tags": [
        "全国勝率6.97はレース内1位",
        "1号艇（イン）"
      ]
    },
    {
      "venue": {
        "code": "03",
        "name": "江戸川"
      },
      "race_no": 1,
      "close_scheduled_at": "2026-07-24T11:14:00+09:00",
      "probs": {
        "1": 0.4905,
        "2": 0.0927,
        "3": 0.2753,
        "4": 0.0835,
        "5": 0.0328,
        "6": 0.0251
      },
      "top_pick": 1,
      "confidence": 0.4905,
      "reason_tags": [
        "1号艇（イン）"
      ]
    },
    {
      "venue": {
        "code": "03",
        "name": "江戸川"
      },
      "race_no": 2,
      "close_scheduled_at": "2026-07-24T11:41:00+09:00",
      "probs": {
        "1": 0.1823,
        "2": 0.394,
        "3": 0.2416,
        "4": 0.0779,
        "5": 0.0808,
        "6": 0.0233
      },
      "top_pick": 2,
      "confidence": 0.394,
      "reason_tags": [
        "モーター2連率52%はレース内1位"
      ]
    },
    {
      "venue": {
        "code": "03",
        "name": "江戸川"
      },
      "race_no": 3,
      "close_scheduled_at": "2026-07-24T12:08:00+09:00",
      "probs": {
        "1": 0.3295,
        "2": 0.1144,
        "3": 0.2932,
        "4": 0.0741,
        "5": 0.1562,
        "6": 0.0326
      },
      "top_pick": 1,
      "confidence": 0.3295,
      "reason_tags": [
        "1号艇（イン）"
      ]
    },
    {
      "venue": {
        "code": "03",
        "name": "江戸川"
      },
      "race_no": 4,
      "close_scheduled_at": "2026-07-24T12:35:00+09:00",
      "probs": {
        "1": 0.1924,
        "2": 0.1481,
        "3": 0.3943,
        "4": 0.0583,
        "5": 0.1676,
        "6": 0.0393
      },
      "top_pick": 3,
      "confidence": 0.3943,
      "reason_tags": [
        "当地勝率7.24はレース内1位",
        "モーター2連率52%はレース内1位"
      ]
    },
    {
      "venue": {
        "code": "03",
        "name": "江戸川"
      },
      "race_no": 5,
      "close_scheduled_at": "2026-07-24T13:02:00+09:00",
      "probs": {
        "1": 0.2421,
        "2": 0.0616,
        "3": 0.4058,
        "4": 0.2385,
        "5": 0.0437,
        "6": 0.0082
      },
      "top_pick": 3,
      "confidence": 0.4058,
      "reason_tags": [
        "全国勝率7.18はレース内1位",
        "当地勝率6.92はレース内1位"
      ]
    },
    {
      "venue": {
        "code": "03",
        "name": "江戸川"
      },
      "race_no": 6,
      "close_scheduled_at": "2026-07-24T13:29:00+09:00",
      "probs": {
        "1": 0.2107,
        "2": 0.1393,
        "3": 0.0466,
        "4": 0.5448,
        "5": 0.0441,
        "6": 0.0145
      },
      "top_pick": 4,
      "confidence": 0.5448,
      "reason_tags": [
        "全国勝率7.21はレース内1位",
        "当地勝率8.16はレース内1位"
      ]
    },
    {
      "venue": {
        "code": "03",
        "name": "江戸川"
      },
      "race_no": 7,
      "close_scheduled_at": "2026-07-24T13:56:00+09:00",
      "probs": {
        "1": 0.6733,
        "2": 0.0384,
        "3": 0.1873,
        "4": 0.0573,
        "5": 0.0323,
        "6": 0.0113
      },
      "top_pick": 1,
      "confidence": 0.6733,
      "reason_tags": [
        "全国勝率6.74はレース内1位",
        "当地勝率7.42はレース内1位"
      ]
    },
    {
      "venue": {
        "code": "03",
        "name": "江戸川"
      },
      "race_no": 8,
      "close_scheduled_at": "2026-07-24T14:24:00+09:00",
      "probs": {
        "1": 0.5931,
        "2": 0.0736,
        "3": 0.202,
        "4": 0.0698,
        "5": 0.052,
        "6": 0.0095
      },
      "top_pick": 1,
      "confidence": 0.5931,
      "reason_tags": [
        "当地勝率6.81はレース内1位",
        "1号艇（イン）"
      ]
    },
    {
      "venue": {
        "code": "03",
        "name": "江戸川"
      },
      "race_no": 9,
      "close_scheduled_at": "2026-07-24T14:52:00+09:00",
      "probs": {
        "1": 0.6397,
        "2": 0.0868,
        "3": 0.0449,
        "4": 0.0585,
        "5": 0.0502,
        "6": 0.1199
      },
      "top_pick": 1,
      "confidence": 0.6397,
      "reason_tags": [
        "1号艇（イン）"
      ]
    },
    {
      "venue": {
        "code": "03",
        "name": "江戸川"
      },
      "race_no": 10,
      "close_scheduled_at": "2026-07-24T15:22:00+09:00",
      "probs": {
        "1": 0.6359,
        "2": 0.0411,
        "3": 0.2057,
        "4": 0.0319,
        "5": 0.0563,
        "6": 0.0291
      },
      "top_pick": 1,
      "confidence": 0.6359,
      "reason_tags": [
        "1号艇（イン）"
      ]
    },
    {
      "venue": {
        "code": "03",
        "name": "江戸川"
      },
      "race_no": 11,
      "close_scheduled_at": "2026-07-24T15:53:00+09:00",
      "probs": {
        "1": 0.4769,
        "2": 0.348,
        "3": 0.096,
        "4": 0.0354,
        "5": 0.0364,
        "6": 0.0072
      },
      "top_pick": 1,
      "confidence": 0.4769,
      "reason_tags": [
        "1号艇（イン）"
      ]
    },
    {
      "venue": {
        "code": "03",
        "name": "江戸川"
      },
      "race_no": 12,
      "close_scheduled_at": "2026-07-24T16:25:00+09:00",
      "probs": {
        "1": 0.7064,
        "2": 0.141,
        "3": 0.0355,
        "4": 0.067,
        "5": 0.0192,
        "6": 0.0308
      },
      "top_pick": 1,
      "confidence": 0.7064,
      "reason_tags": [
        "全国勝率7.18はレース内1位",
        "1号艇（イン）"
      ]
    },
    {
      "venue": {
        "code": "06",
        "name": "浜名湖"
      },
      "race_no": 1,
      "close_scheduled_at": "2026-07-24T11:32:00+09:00",
      "probs": {
        "1": 0.5402,
        "2": 0.1032,
        "3": 0.1296,
        "4": 0.1542,
        "5": 0.0665,
        "6": 0.0064
      },
      "top_pick": 1,
      "confidence": 0.5402,
      "reason_tags": [
        "モーター2連率47%はレース内1位",
        "1号艇（イン）"
      ]
    },
    {
      "venue": {
        "code": "06",
        "name": "浜名湖"
      },
      "race_no": 2,
      "close_scheduled_at": "2026-07-24T12:03:00+09:00",
      "probs": {
        "1": 0.6493,
        "2": 0.1031,
        "3": 0.0641,
        "4": 0.1114,
        "5": 0.0478,
        "6": 0.0243
      },
      "top_pick": 1,
      "confidence": 0.6493,
      "reason_tags": [
        "全国勝率6.05はレース内1位",
        "当地勝率6.00はレース内1位"
      ]
    },
    {
      "venue": {
        "code": "06",
        "name": "浜名湖"
      },
      "race_no": 3,
      "close_scheduled_at": "2026-07-24T12:33:00+09:00",
      "probs": {
        "1": 0.2518,
        "2": 0.4166,
        "3": 0.1439,
        "4": 0.1267,
        "5": 0.0321,
        "6": 0.0289
      },
      "top_pick": 2,
      "confidence": 0.4166,
      "reason_tags": [
        "全国勝率6.80はレース内1位",
        "レース内で唯一のA1級"
      ]
    },
    {
      "venue": {
        "code": "06",
        "name": "浜名湖"
      },
      "race_no": 4,
      "close_scheduled_at": "2026-07-24T13:09:00+09:00",
      "probs": {
        "1": 0.7773,
        "2": 0.0581,
        "3": 0.0812,
        "4": 0.0157,
        "5": 0.0576,
        "6": 0.0102
      },
      "top_pick": 1,
      "confidence": 0.7773,
      "reason_tags": [
        "全国勝率6.37はレース内1位",
        "当地勝率6.15はレース内1位"
      ]
    },
    {
      "venue": {
        "code": "06",
        "name": "浜名湖"
      },
      "race_no": 5,
      "close_scheduled_at": "2026-07-24T13:39:00+09:00",
      "probs": {
        "1": 0.3734,
        "2": 0.2861,
        "3": 0.1547,
        "4": 0.1589,
        "5": 0.0232,
        "6": 0.0037
      },
      "top_pick": 1,
      "confidence": 0.3734,
      "reason_tags": [
        "モーター2連率36%はレース内1位",
        "1号艇（イン）"
      ]
    },
    {
      "venue": {
        "code": "06",
        "name": "浜名湖"
      },
      "race_no": 6,
      "close_scheduled_at": "2026-07-24T14:05:00+09:00",
      "probs": {
        "1": 0.3664,
        "2": 0.0664,
        "3": 0.3622,
        "4": 0.0457,
        "5": 0.1249,
        "6": 0.0344
      },
      "top_pick": 1,
      "confidence": 0.3664,
      "reason_tags": [
        "当地勝率6.50はレース内1位",
        "1号艇（イン）"
      ]
    },
    {
      "venue": {
        "code": "06",
        "name": "浜名湖"
      },
      "race_no": 7,
      "close_scheduled_at": "2026-07-24T14:37:00+09:00",
      "probs": {
        "1": 0.2926,
        "2": 0.1028,
        "3": 0.309,
        "4": 0.0591,
        "5": 0.0839,
        "6": 0.1526
      },
      "top_pick": 3,
      "confidence": 0.309,
      "reason_tags": [
        "モーター2連率48%はレース内1位"
      ]
    },
    {
      "venue": {
        "code": "06",
        "name": "浜名湖"
      },
      "race_no": 8,
      "close_scheduled_at": "2026-07-24T15:06:00+09:00",
      "probs": {
        "1": 0.7559,
        "2": 0.0439,
        "3": 0.0213,
        "4": 0.1412,
        "5": 0.0237,
        "6": 0.014
      },
      "top_pick": 1,
      "confidence": 0.7559,
      "reason_tags": [
        "全国勝率7.02はレース内1位",
        "1号艇（イン）"
      ]
    },
    {
      "venue": {
        "code": "06",
        "name": "浜名湖"
      },
      "race_no": 9,
      "close_scheduled_at": "2026-07-24T15:35:00+09:00",
      "probs": {
        "1": 0.5488,
        "2": 0.1555,
        "3": 0.0857,
        "4": 0.1847,
        "5": 0.0136,
        "6": 0.0117
      },
      "top_pick": 1,
      "confidence": 0.5488,
      "reason_tags": [
        "モーター2連率45%はレース内1位",
        "1号艇（イン）"
      ]
    },
    {
      "venue": {
        "code": "06",
        "name": "浜名湖"
      },
      "race_no": 10,
      "close_scheduled_at": "2026-07-24T16:09:00+09:00",
      "probs": {
        "1": 0.4736,
        "2": 0.1556,
        "3": 0.1183,
        "4": 0.185,
        "5": 0.0525,
        "6": 0.0151
      },
      "top_pick": 1,
      "confidence": 0.4736,
      "reason_tags": [
        "1号艇（イン）"
      ]
    },
    {
      "venue": {
        "code": "06",
        "name": "浜名湖"
      },
      "race_no": 11,
      "close_scheduled_at": "2026-07-24T16:36:00+09:00",
      "probs": {
        "1": 0.678,
        "2": 0.1624,
        "3": 0.0735,
        "4": 0.05,
        "5": 0.0177,
        "6": 0.0184
      },
      "top_pick": 1,
      "confidence": 0.678,
      "reason_tags": [
        "全国勝率6.63はレース内1位",
        "当地勝率6.22はレース内1位"
      ]
    },
    {
      "venue": {
        "code": "06",
        "name": "浜名湖"
      },
      "race_no": 12,
      "close_scheduled_at": "2026-07-24T17:07:00+09:00",
      "probs": {
        "1": 0.5779,
        "2": 0.0739,
        "3": 0.1572,
        "4": 0.086,
        "5": 0.0579,
        "6": 0.0471
      },
      "top_pick": 1,
      "confidence": 0.5779,
      "reason_tags": [
        "1号艇（イン）"
      ]
    },
    {
      "venue": {
        "code": "08",
        "name": "常滑"
      },
      "race_no": 1,
      "close_scheduled_at": "2026-07-24T10:40:00+09:00",
      "probs": {
        "1": 0.8619,
        "2": 0.0408,
        "3": 0.0244,
        "4": 0.0344,
        "5": 0.0206,
        "6": 0.0179
      },
      "top_pick": 1,
      "confidence": 0.8619,
      "reason_tags": [
        "全国勝率6.45はレース内1位",
        "当地勝率6.50はレース内1位"
      ]
    },
    {
      "venue": {
        "code": "08",
        "name": "常滑"
      },
      "race_no": 2,
      "close_scheduled_at": "2026-07-24T11:08:00+09:00",
      "probs": {
        "1": 0.281,
        "2": 0.4687,
        "3": 0.0529,
        "4": 0.1014,
        "5": 0.0848,
        "6": 0.0112
      },
      "top_pick": 2,
      "confidence": 0.4687,
      "reason_tags": [
        "全国勝率7.55はレース内1位",
        "当地勝率7.50はレース内1位"
      ]
    },
    {
      "venue": {
        "code": "08",
        "name": "常滑"
      },
      "race_no": 3,
      "close_scheduled_at": "2026-07-24T11:36:00+09:00",
      "probs": {
        "1": 0.3473,
        "2": 0.2724,
        "3": 0.0898,
        "4": 0.2346,
        "5": 0.0168,
        "6": 0.0391
      },
      "top_pick": 1,
      "confidence": 0.3473,
      "reason_tags": [
        "1号艇（イン）"
      ]
    },
    {
      "venue": {
        "code": "08",
        "name": "常滑"
      },
      "race_no": 4,
      "close_scheduled_at": "2026-07-24T12:05:00+09:00",
      "probs": {
        "1": 0.4556,
        "2": 0.092,
        "3": 0.1763,
        "4": 0.1783,
        "5": 0.012,
        "6": 0.0858
      },
      "top_pick": 1,
      "confidence": 0.4556,
      "reason_tags": [
        "1号艇（イン）"
      ]
    },
    {
      "venue": {
        "code": "08",
        "name": "常滑"
      },
      "race_no": 5,
      "close_scheduled_at": "2026-07-24T12:31:00+09:00",
      "probs": {
        "1": 0.5034,
        "2": 0.1282,
        "3": 0.0432,
        "4": 0.2048,
        "5": 0.102,
        "6": 0.0184
      },
      "top_pick": 1,
      "confidence": 0.5034,
      "reason_tags": [
        "1号艇（イン）"
      ]
    },
    {
      "venue": {
        "code": "08",
        "name": "常滑"
      },
      "race_no": 6,
      "close_scheduled_at": "2026-07-24T13:00:00+09:00",
      "probs": {
        "1": 0.4567,
        "2": 0.0616,
        "3": 0.2661,
        "4": 0.0498,
        "5": 0.0143,
        "6": 0.1514
      },
      "top_pick": 1,
      "confidence": 0.4567,
      "reason_tags": [
        "1号艇（イン）"
      ]
    },
    {
      "venue": {
        "code": "08",
        "name": "常滑"
      },
      "race_no": 7,
      "close_scheduled_at": "2026-07-24T13:27:00+09:00",
      "probs": {
        "1": 0.5931,
        "2": 0.1378,
        "3": 0.0349,
        "4": 0.2012,
        "5": 0.0247,
        "6": 0.0083
      },
      "top_pick": 1,
      "confidence": 0.5931,
      "reason_tags": [
        "モーター2連率43%はレース内1位",
        "1号艇（イン）"
      ]
    },
    {
      "venue": {
        "code": "08",
        "name": "常滑"
      },
      "race_no": 8,
      "close_scheduled_at": "2026-07-24T13:58:00+09:00",
      "probs": {
        "1": 0.5631,
        "2": 0.1096,
        "3": 0.0851,
        "4": 0.1698,
        "5": 0.0683,
        "6": 0.0042
      },
      "top_pick": 1,
      "confidence": 0.5631,
      "reason_tags": [
        "全国勝率5.89はレース内1位",
        "1号艇（イン）"
      ]
    },
    {
      "venue": {
        "code": "08",
        "name": "常滑"
      },
      "race_no": 9,
      "close_scheduled_at": "2026-07-24T14:30:00+09:00",
      "probs": {
        "1": 0.2197,
        "2": 0.1415,
        "3": 0.3072,
        "4": 0.0245,
        "5": 0.2736,
        "6": 0.0335
      },
      "top_pick": 3,
      "confidence": 0.3072,
      "reason_tags": [
        "モーター2連率46%はレース内1位"
      ]
    },
    {
      "venue": {
        "code": "08",
        "name": "常滑"
      },
      "race_no": 10,
      "close_scheduled_at": "2026-07-24T14:58:00+09:00",
      "probs": {
        "1": 0.2803,
        "2": 0.3304,
        "3": 0.2338,
        "4": 0.0367,
        "5": 0.047,
        "6": 0.0717
      },
      "top_pick": 2,
      "confidence": 0.3304,
      "reason_tags": [
        "全国勝率6.80はレース内1位",
        "当地勝率7.29はレース内1位"
      ]
    },
    {
      "venue": {
        "code": "08",
        "name": "常滑"
      },
      "race_no": 11,
      "close_scheduled_at": "2026-07-24T15:33:00+09:00",
      "probs": {
        "1": 0.721,
        "2": 0.1038,
        "3": 0.0794,
        "4": 0.0257,
        "5": 0.0649,
        "6": 0.0052
      },
      "top_pick": 1,
      "confidence": 0.721,
      "reason_tags": [
        "当地勝率7.50はレース内1位",
        "1号艇（イン）"
      ]
    },
    {
      "venue": {
        "code": "08",
        "name": "常滑"
      },
      "race_no": 12,
      "close_scheduled_at": "2026-07-24T16:06:00+09:00",
      "probs": {
        "1": 0.8143,
        "2": 0.0371,
        "3": 0.0591,
        "4": 0.0637,
        "5": 0.0198,
        "6": 0.006
      },
      "top_pick": 1,
      "confidence": 0.8143,
      "reason_tags": [
        "全国勝率7.07はレース内1位",
        "当地勝率6.53はレース内1位"
      ]
    },
    {
      "venue": {
        "code": "12",
        "name": "住之江"
      },
      "race_no": 1,
      "close_scheduled_at": "2026-07-24T15:18:00+09:00",
      "probs": {
        "1": 0.3948,
        "2": 0.1015,
        "3": 0.3184,
        "4": 0.0595,
        "5": 0.0669,
        "6": 0.0589
      },
      "top_pick": 1,
      "confidence": 0.3948,
      "reason_tags": [
        "1号艇（イン）"
      ]
    },
    {
      "venue": {
        "code": "12",
        "name": "住之江"
      },
      "race_no": 2,
      "close_scheduled_at": "2026-07-24T15:57:00+09:00",
      "probs": {
        "1": 0.5205,
        "2": 0.0907,
        "3": 0.0851,
        "4": 0.2599,
        "5": 0.0384,
        "6": 0.0055
      },
      "top_pick": 1,
      "confidence": 0.5205,
      "reason_tags": [
        "1号艇（イン）"
      ]
    },
    {
      "venue": {
        "code": "12",
        "name": "住之江"
      },
      "race_no": 3,
      "close_scheduled_at": "2026-07-24T16:31:00+09:00",
      "probs": {
        "1": 0.6199,
        "2": 0.1257,
        "3": 0.1808,
        "4": 0.0523,
        "5": 0.011,
        "6": 0.0103
      },
      "top_pick": 1,
      "confidence": 0.6199,
      "reason_tags": [
        "1号艇（イン）"
      ]
    },
    {
      "venue": {
        "code": "12",
        "name": "住之江"
      },
      "race_no": 4,
      "close_scheduled_at": "2026-07-24T17:04:00+09:00",
      "probs": {
        "1": 0.7779,
        "2": 0.0301,
        "3": 0.0868,
        "4": 0.0347,
        "5": 0.0173,
        "6": 0.0532
      },
      "top_pick": 1,
      "confidence": 0.7779,
      "reason_tags": [
        "全国勝率6.09はレース内1位",
        "当地勝率6.90はレース内1位"
      ]
    },
    {
      "venue": {
        "code": "12",
        "name": "住之江"
      },
      "race_no": 5,
      "close_scheduled_at": "2026-07-24T17:28:00+09:00",
      "probs": {
        "1": 0.8803,
        "2": 0.0349,
        "3": 0.0219,
        "4": 0.0432,
        "5": 0.0097,
        "6": 0.01
      },
      "top_pick": 1,
      "confidence": 0.8803,
      "reason_tags": [
        "全国勝率7.10はレース内1位",
        "当地勝率5.78はレース内1位"
      ]
    },
    {
      "venue": {
        "code": "12",
        "name": "住之江"
      },
      "race_no": 6,
      "close_scheduled_at": "2026-07-24T17:55:00+09:00",
      "probs": {
        "1": 0.442,
        "2": 0.0429,
        "3": 0.3788,
        "4": 0.0582,
        "5": 0.0174,
        "6": 0.0606
      },
      "top_pick": 1,
      "confidence": 0.442,
      "reason_tags": [
        "1号艇（イン）"
      ]
    },
    {
      "venue": {
        "code": "12",
        "name": "住之江"
      },
      "race_no": 7,
      "close_scheduled_at": "2026-07-24T18:19:00+09:00",
      "probs": {
        "1": 0.4926,
        "2": 0.0404,
        "3": 0.3237,
        "4": 0.1053,
        "5": 0.018,
        "6": 0.0199
      },
      "top_pick": 1,
      "confidence": 0.4926,
      "reason_tags": [
        "1号艇（イン）"
      ]
    },
    {
      "venue": {
        "code": "12",
        "name": "住之江"
      },
      "race_no": 8,
      "close_scheduled_at": "2026-07-24T18:45:00+09:00",
      "probs": {
        "1": 0.8252,
        "2": 0.0353,
        "3": 0.0566,
        "4": 0.0274,
        "5": 0.0251,
        "6": 0.0304
      },
      "top_pick": 1,
      "confidence": 0.8252,
      "reason_tags": [
        "全国勝率6.57はレース内1位",
        "レース内で唯一のA1級"
      ]
    },
    {
      "venue": {
        "code": "12",
        "name": "住之江"
      },
      "race_no": 9,
      "close_scheduled_at": "2026-07-24T19:14:00+09:00",
      "probs": {
        "1": 0.6738,
        "2": 0.0654,
        "3": 0.0844,
        "4": 0.1148,
        "5": 0.0241,
        "6": 0.0376
      },
      "top_pick": 1,
      "confidence": 0.6738,
      "reason_tags": [
        "当地勝率6.15はレース内1位",
        "1号艇（イン）"
      ]
    },
    {
      "venue": {
        "code": "12",
        "name": "住之江"
      },
      "race_no": 10,
      "close_scheduled_at": "2026-07-24T19:41:00+09:00",
      "probs": {
        "1": 0.7165,
        "2": 0.0433,
        "3": 0.1001,
        "4": 0.0343,
        "5": 0.05,
        "6": 0.0558
      },
      "top_pick": 1,
      "confidence": 0.7165,
      "reason_tags": [
        "当地勝率6.18はレース内1位",
        "モーター2連率46%はレース内1位"
      ]
    },
    {
      "venue": {
        "code": "12",
        "name": "住之江"
      },
      "race_no": 11,
      "close_scheduled_at": "2026-07-24T20:07:00+09:00",
      "probs": {
        "1": 0.6809,
        "2": 0.0349,
        "3": 0.1386,
        "4": 0.0283,
        "5": 0.0385,
        "6": 0.0788
      },
      "top_pick": 1,
      "confidence": 0.6809,
      "reason_tags": [
        "1号艇（イン）"
      ]
    },
    {
      "venue": {
        "code": "12",
        "name": "住之江"
      },
      "race_no": 12,
      "close_scheduled_at": "2026-07-24T20:36:00+09:00",
      "probs": {
        "1": 0.6639,
        "2": 0.066,
        "3": 0.1317,
        "4": 0.0758,
        "5": 0.0441,
        "6": 0.0184
      },
      "top_pick": 1,
      "confidence": 0.6639,
      "reason_tags": [
        "全国勝率7.19はレース内1位",
        "当地勝率7.11はレース内1位"
      ]
    },
    {
      "venue": {
        "code": "13",
        "name": "尼崎"
      },
      "race_no": 1,
      "close_scheduled_at": "2026-07-24T10:36:00+09:00",
      "probs": {
        "1": 0.4677,
        "2": 0.0759,
        "3": 0.365,
        "4": 0.0451,
        "5": 0.0098,
        "6": 0.0366
      },
      "top_pick": 1,
      "confidence": 0.4677,
      "reason_tags": [
        "1号艇（イン）"
      ]
    },
    {
      "venue": {
        "code": "13",
        "name": "尼崎"
      },
      "race_no": 2,
      "close_scheduled_at": "2026-07-24T11:03:00+09:00",
      "probs": {
        "1": 0.6763,
        "2": 0.1118,
        "3": 0.0644,
        "4": 0.0179,
        "5": 0.0224,
        "6": 0.1073
      },
      "top_pick": 1,
      "confidence": 0.6763,
      "reason_tags": [
        "当地勝率6.67はレース内1位",
        "1号艇（イン）"
      ]
    },
    {
      "venue": {
        "code": "13",
        "name": "尼崎"
      },
      "race_no": 3,
      "close_scheduled_at": "2026-07-24T11:27:00+09:00",
      "probs": {
        "1": 0.3099,
        "2": 0.3089,
        "3": 0.0671,
        "4": 0.235,
        "5": 0.0307,
        "6": 0.0485
      },
      "top_pick": 1,
      "confidence": 0.3099,
      "reason_tags": [
        "モーター2連率43%はレース内1位",
        "1号艇（イン）"
      ]
    },
    {
      "venue": {
        "code": "13",
        "name": "尼崎"
      },
      "race_no": 4,
      "close_scheduled_at": "2026-07-24T11:52:00+09:00",
      "probs": {
        "1": 0.3382,
        "2": 0.1938,
        "3": 0.0643,
        "4": 0.1706,
        "5": 0.2074,
        "6": 0.0257
      },
      "top_pick": 1,
      "confidence": 0.3382,
      "reason_tags": [
        "1号艇（イン）"
      ]
    },
    {
      "venue": {
        "code": "13",
        "name": "尼崎"
      },
      "race_no": 5,
      "close_scheduled_at": "2026-07-24T12:21:00+09:00",
      "probs": {
        "1": 0.4255,
        "2": 0.1498,
        "3": 0.0641,
        "4": 0.0882,
        "5": 0.2298,
        "6": 0.0426
      },
      "top_pick": 1,
      "confidence": 0.4255,
      "reason_tags": [
        "1号艇（イン）"
      ]
    },
    {
      "venue": {
        "code": "13",
        "name": "尼崎"
      },
      "race_no": 6,
      "close_scheduled_at": "2026-07-24T12:52:00+09:00",
      "probs": {
        "1": 0.7554,
        "2": 0.0851,
        "3": 0.0246,
        "4": 0.1058,
        "5": 0.0226,
        "6": 0.0066
      },
      "top_pick": 1,
      "confidence": 0.7554,
      "reason_tags": [
        "全国勝率6.16はレース内1位",
        "当地勝率6.70はレース内1位"
      ]
    },
    {
      "venue": {
        "code": "13",
        "name": "尼崎"
      },
      "race_no": 7,
      "close_scheduled_at": "2026-07-24T13:20:00+09:00",
      "probs": {
        "1": 0.2867,
        "2": 0.0955,
        "3": 0.0818,
        "4": 0.2332,
        "5": 0.2823,
        "6": 0.0205
      },
      "top_pick": 1,
      "confidence": 0.2867,
      "reason_tags": [
        "1号艇（イン）"
      ]
    },
    {
      "venue": {
        "code": "13",
        "name": "尼崎"
      },
      "race_no": 8,
      "close_scheduled_at": "2026-07-24T13:53:00+09:00",
      "probs": {
        "1": 0.6266,
        "2": 0.185,
        "3": 0.1044,
        "4": 0.0329,
        "5": 0.0387,
        "6": 0.0122
      },
      "top_pick": 1,
      "confidence": 0.6266,
      "reason_tags": [
        "1号艇（イン）"
      ]
    },
    {
      "venue": {
        "code": "13",
        "name": "尼崎"
      },
      "race_no": 9,
      "close_scheduled_at": "2026-07-24T14:42:00+09:00",
      "probs": {
        "1": 0.7018,
        "2": 0.0381,
        "3": 0.1561,
        "4": 0.0688,
        "5": 0.0059,
        "6": 0.0293
      },
      "top_pick": 1,
      "confidence": 0.7018,
      "reason_tags": [
        "全国勝率6.12はレース内1位",
        "モーター2連率41%はレース内1位"
      ]
    },
    {
      "venue": {
        "code": "13",
        "name": "尼崎"
      },
      "race_no": 10,
      "close_scheduled_at": "2026-07-24T15:11:00+09:00",
      "probs": {
        "1": 0.6158,
        "2": 0.1041,
        "3": 0.0933,
        "4": 0.1155,
        "5": 0.0627,
        "6": 0.0085
      },
      "top_pick": 1,
      "confidence": 0.6158,
      "reason_tags": [
        "当地勝率6.75はレース内1位",
        "レース内で唯一のA1級"
      ]
    },
    {
      "venue": {
        "code": "13",
        "name": "尼崎"
      },
      "race_no": 11,
      "close_scheduled_at": "2026-07-24T15:51:00+09:00",
      "probs": {
        "1": 0.5123,
        "2": 0.2153,
        "3": 0.0256,
        "4": 0.0659,
        "5": 0.1655,
        "6": 0.0153
      },
      "top_pick": 1,
      "confidence": 0.5123,
      "reason_tags": [
        "1号艇（イン）"
      ]
    },
    {
      "venue": {
        "code": "13",
        "name": "尼崎"
      },
      "race_no": 12,
      "close_scheduled_at": "2026-07-24T16:23:00+09:00",
      "probs": {
        "1": 0.6369,
        "2": 0.1281,
        "3": 0.0765,
        "4": 0.0412,
        "5": 0.1048,
        "6": 0.0126
      },
      "top_pick": 1,
      "confidence": 0.6369,
      "reason_tags": [
        "当地勝率7.94はレース内1位",
        "1号艇（イン）"
      ]
    },
    {
      "venue": {
        "code": "14",
        "name": "鳴門"
      },
      "race_no": 1,
      "close_scheduled_at": "2026-07-24T08:46:00+09:00",
      "probs": {
        "1": 0.8354,
        "2": 0.0333,
        "3": 0.0544,
        "4": 0.0459,
        "5": 0.0134,
        "6": 0.0176
      },
      "top_pick": 1,
      "confidence": 0.8354,
      "reason_tags": [
        "全国勝率6.55はレース内1位",
        "当地勝率5.84はレース内1位"
      ]
    },
    {
      "venue": {
        "code": "14",
        "name": "鳴門"
      },
      "race_no": 2,
      "close_scheduled_at": "2026-07-24T09:12:00+09:00",
      "probs": {
        "1": 0.2031,
        "2": 0.114,
        "3": 0.4093,
        "4": 0.1074,
        "5": 0.1149,
        "6": 0.0513
      },
      "top_pick": 3,
      "confidence": 0.4093,
      "reason_tags": [
        "全国勝率6.47はレース内1位",
        "レース内で唯一のA1級"
      ]
    },
    {
      "venue": {
        "code": "14",
        "name": "鳴門"
      },
      "race_no": 3,
      "close_scheduled_at": "2026-07-24T09:38:00+09:00",
      "probs": {
        "1": 0.5029,
        "2": 0.0481,
        "3": 0.2271,
        "4": 0.0302,
        "5": 0.1824,
        "6": 0.0093
      },
      "top_pick": 1,
      "confidence": 0.5029,
      "reason_tags": [
        "1号艇（イン）"
      ]
    },
    {
      "venue": {
        "code": "14",
        "name": "鳴門"
      },
      "race_no": 4,
      "close_scheduled_at": "2026-07-24T10:04:00+09:00",
      "probs": {
        "1": 0.8368,
        "2": 0.0474,
        "3": 0.0257,
        "4": 0.0407,
        "5": 0.017,
        "6": 0.0323
      },
      "top_pick": 1,
      "confidence": 0.8368,
      "reason_tags": [
        "全国勝率6.85はレース内1位",
        "レース内で唯一のA1級"
      ]
    },
    {
      "venue": {
        "code": "14",
        "name": "鳴門"
      },
      "race_no": 5,
      "close_scheduled_at": "2026-07-24T10:30:00+09:00",
      "probs": {
        "1": 0.2747,
        "2": 0.031,
        "3": 0.5532,
        "4": 0.0484,
        "5": 0.0818,
        "6": 0.0109
      },
      "top_pick": 3,
      "confidence": 0.5532,
      "reason_tags": [
        "全国勝率7.06はレース内1位",
        "当地勝率7.12はレース内1位"
      ]
    },
    {
      "venue": {
        "code": "14",
        "name": "鳴門"
      },
      "race_no": 6,
      "close_scheduled_at": "2026-07-24T10:59:00+09:00",
      "probs": {
        "1": 0.0816,
        "2": 0.105,
        "3": 0.4253,
        "4": 0.2263,
        "5": 0.1585,
        "6": 0.0033
      },
      "top_pick": 3,
      "confidence": 0.4253,
      "reason_tags": [
        "全国勝率7.11はレース内1位",
        "当地勝率6.81はレース内1位"
      ]
    },
    {
      "venue": {
        "code": "14",
        "name": "鳴門"
      },
      "race_no": 7,
      "close_scheduled_at": "2026-07-24T11:28:00+09:00",
      "probs": {
        "1": 0.1435,
        "2": 0.3077,
        "3": 0.1705,
        "4": 0.1407,
        "5": 0.0714,
        "6": 0.1662
      },
      "top_pick": 2,
      "confidence": 0.3077,
      "reason_tags": []
    },
    {
      "venue": {
        "code": "14",
        "name": "鳴門"
      },
      "race_no": 8,
      "close_scheduled_at": "2026-07-24T11:58:00+09:00",
      "probs": {
        "1": 0.3303,
        "2": 0.1143,
        "3": 0.2801,
        "4": 0.2184,
        "5": 0.0428,
        "6": 0.014
      },
      "top_pick": 1,
      "confidence": 0.3303,
      "reason_tags": [
        "1号艇（イン）"
      ]
    },
    {
      "venue": {
        "code": "14",
        "name": "鳴門"
      },
      "race_no": 9,
      "close_scheduled_at": "2026-07-24T12:27:00+09:00",
      "probs": {
        "1": 0.6958,
        "2": 0.1652,
        "3": 0.0392,
        "4": 0.0169,
        "5": 0.0709,
        "6": 0.0121
      },
      "top_pick": 1,
      "confidence": 0.6958,
      "reason_tags": [
        "全国勝率6.36はレース内1位",
        "当地勝率6.15はレース内1位"
      ]
    },
    {
      "venue": {
        "code": "14",
        "name": "鳴門"
      },
      "race_no": 10,
      "close_scheduled_at": "2026-07-24T13:05:00+09:00",
      "probs": {
        "1": 0.3541,
        "2": 0.2691,
        "3": 0.2541,
        "4": 0.1037,
        "5": 0.0053,
        "6": 0.0137
      },
      "top_pick": 1,
      "confidence": 0.3541,
      "reason_tags": [
        "1号艇（イン）"
      ]
    },
    {
      "venue": {
        "code": "14",
        "name": "鳴門"
      },
      "race_no": 11,
      "close_scheduled_at": "2026-07-24T13:35:00+09:00",
      "probs": {
        "1": 0.5243,
        "2": 0.2377,
        "3": 0.0603,
        "4": 0.1319,
        "5": 0.0252,
        "6": 0.0206
      },
      "top_pick": 1,
      "confidence": 0.5243,
      "reason_tags": [
        "当地勝率7.60はレース内1位",
        "1号艇（イン）"
      ]
    },
    {
      "venue": {
        "code": "14",
        "name": "鳴門"
      },
      "race_no": 12,
      "close_scheduled_at": "2026-07-24T14:13:00+09:00",
      "probs": {
        "1": 0.7283,
        "2": 0.1056,
        "3": 0.1017,
        "4": 0.0248,
        "5": 0.0097,
        "6": 0.0299
      },
      "top_pick": 1,
      "confidence": 0.7283,
      "reason_tags": [
        "全国勝率7.11はレース内1位",
        "1号艇（イン）"
      ]
    },
    {
      "venue": {
        "code": "15",
        "name": "丸亀"
      },
      "race_no": 1,
      "close_scheduled_at": "2026-07-24T15:27:00+09:00",
      "probs": {
        "1": 0.7569,
        "2": 0.0641,
        "3": 0.0693,
        "4": 0.0342,
        "5": 0.0712,
        "6": 0.0044
      },
      "top_pick": 1,
      "confidence": 0.7569,
      "reason_tags": [
        "全国勝率5.13はレース内1位",
        "当地勝率5.56はレース内1位"
      ]
    },
    {
      "venue": {
        "code": "15",
        "name": "丸亀"
      },
      "race_no": 2,
      "close_scheduled_at": "2026-07-24T16:02:00+09:00",
      "probs": {
        "1": 0.3234,
        "2": 0.2444,
        "3": 0.2263,
        "4": 0.0768,
        "5": 0.0141,
        "6": 0.115
      },
      "top_pick": 1,
      "confidence": 0.3234,
      "reason_tags": [
        "1号艇（イン）"
      ]
    },
    {
      "venue": {
        "code": "15",
        "name": "丸亀"
      },
      "race_no": 3,
      "close_scheduled_at": "2026-07-24T16:33:00+09:00",
      "probs": {
        "1": 0.2949,
        "2": 0.0926,
        "3": 0.233,
        "4": 0.1004,
        "5": 0.1035,
        "6": 0.1756
      },
      "top_pick": 1,
      "confidence": 0.2949,
      "reason_tags": [
        "モーター2連率41%はレース内1位",
        "1号艇（イン）"
      ]
    },
    {
      "venue": {
        "code": "15",
        "name": "丸亀"
      },
      "race_no": 4,
      "close_scheduled_at": "2026-07-24T17:09:00+09:00",
      "probs": {
        "1": 0.5182,
        "2": 0.0518,
        "3": 0.0314,
        "4": 0.1658,
        "5": 0.0814,
        "6": 0.1513
      },
      "top_pick": 1,
      "confidence": 0.5182,
      "reason_tags": [
        "1号艇（イン）"
      ]
    },
    {
      "venue": {
        "code": "15",
        "name": "丸亀"
      },
      "race_no": 5,
      "close_scheduled_at": "2026-07-24T17:33:00+09:00",
      "probs": {
        "1": 0.6368,
        "2": 0.0856,
        "3": 0.0504,
        "4": 0.143,
        "5": 0.0159,
        "6": 0.0684
      },
      "top_pick": 1,
      "confidence": 0.6368,
      "reason_tags": [
        "1号艇（イン）"
      ]
    },
    {
      "venue": {
        "code": "15",
        "name": "丸亀"
      },
      "race_no": 6,
      "close_scheduled_at": "2026-07-24T17:58:00+09:00",
      "probs": {
        "1": 0.7705,
        "2": 0.0319,
        "3": 0.0594,
        "4": 0.0151,
        "5": 0.061,
        "6": 0.0621
      },
      "top_pick": 1,
      "confidence": 0.7705,
      "reason_tags": [
        "1号艇（イン）"
      ]
    },
    {
      "venue": {
        "code": "15",
        "name": "丸亀"
      },
      "race_no": 7,
      "close_scheduled_at": "2026-07-24T18:24:00+09:00",
      "probs": {
        "1": 0.7799,
        "2": 0.0291,
        "3": 0.0274,
        "4": 0.0622,
        "5": 0.0275,
        "6": 0.0739
      },
      "top_pick": 1,
      "confidence": 0.7799,
      "reason_tags": [
        "1号艇（イン）"
      ]
    },
    {
      "venue": {
        "code": "15",
        "name": "丸亀"
      },
      "race_no": 8,
      "close_scheduled_at": "2026-07-24T18:50:00+09:00",
      "probs": {
        "1": 0.728,
        "2": 0.1088,
        "3": 0.047,
        "4": 0.0906,
        "5": 0.0229,
        "6": 0.0027
      },
      "top_pick": 1,
      "confidence": 0.728,
      "reason_tags": [
        "全国勝率6.40はレース内1位",
        "当地勝率6.25はレース内1位"
      ]
    },
    {
      "venue": {
        "code": "15",
        "name": "丸亀"
      },
      "race_no": 9,
      "close_scheduled_at": "2026-07-24T19:19:00+09:00",
      "probs": {
        "1": 0.8558,
        "2": 0.0303,
        "3": 0.0612,
        "4": 0.0173,
        "5": 0.0322,
        "6": 0.0031
      },
      "top_pick": 1,
      "confidence": 0.8558,
      "reason_tags": [
        "全国勝率7.16はレース内1位",
        "1号艇（イン）"
      ]
    },
    {
      "venue": {
        "code": "15",
        "name": "丸亀"
      },
      "race_no": 10,
      "close_scheduled_at": "2026-07-24T19:46:00+09:00",
      "probs": {
        "1": 0.7856,
        "2": 0.0924,
        "3": 0.0649,
        "4": 0.0394,
        "5": 0.0126,
        "6": 0.0051
      },
      "top_pick": 1,
      "confidence": 0.7856,
      "reason_tags": [
        "全国勝率7.19はレース内1位",
        "当地勝率6.85はレース内1位"
      ]
    },
    {
      "venue": {
        "code": "15",
        "name": "丸亀"
      },
      "race_no": 11,
      "close_scheduled_at": "2026-07-24T20:12:00+09:00",
      "probs": {
        "1": 0.7624,
        "2": 0.0879,
        "3": 0.0605,
        "4": 0.0442,
        "5": 0.0197,
        "6": 0.0253
      },
      "top_pick": 1,
      "confidence": 0.7624,
      "reason_tags": [
        "全国勝率7.41はレース内1位",
        "当地勝率7.40はレース内1位"
      ]
    },
    {
      "venue": {
        "code": "15",
        "name": "丸亀"
      },
      "race_no": 12,
      "close_scheduled_at": "2026-07-24T20:41:00+09:00",
      "probs": {
        "1": 0.5905,
        "2": 0.0706,
        "3": 0.1391,
        "4": 0.1722,
        "5": 0.0222,
        "6": 0.0054
      },
      "top_pick": 1,
      "confidence": 0.5905,
      "reason_tags": [
        "モーター2連率37%はレース内1位",
        "1号艇（イン）"
      ]
    },
    {
      "venue": {
        "code": "17",
        "name": "宮島"
      },
      "race_no": 1,
      "close_scheduled_at": "2026-07-24T10:56:00+09:00",
      "probs": {
        "1": 0.6815,
        "2": 0.0785,
        "3": 0.083,
        "4": 0.0552,
        "5": 0.0574,
        "6": 0.0444
      },
      "top_pick": 1,
      "confidence": 0.6815,
      "reason_tags": [
        "全国勝率5.79はレース内1位",
        "1号艇（イン）"
      ]
    },
    {
      "venue": {
        "code": "17",
        "name": "宮島"
      },
      "race_no": 2,
      "close_scheduled_at": "2026-07-24T11:39:00+09:00",
      "probs": {
        "1": 0.4675,
        "2": 0.2873,
        "3": 0.1372,
        "4": 0.036,
        "5": 0.0577,
        "6": 0.0143
      },
      "top_pick": 1,
      "confidence": 0.4675,
      "reason_tags": [
        "1号艇（イン）"
      ]
    },
    {
      "venue": {
        "code": "17",
        "name": "宮島"
      },
      "race_no": 3,
      "close_scheduled_at": "2026-07-24T12:12:00+09:00",
      "probs": {
        "1": 0.4461,
        "2": 0.2803,
        "3": 0.0701,
        "4": 0.1835,
        "5": 0.01,
        "6": 0.01
      },
      "top_pick": 1,
      "confidence": 0.4461,
      "reason_tags": [
        "1号艇（イン）"
      ]
    },
    {
      "venue": {
        "code": "17",
        "name": "宮島"
      },
      "race_no": 4,
      "close_scheduled_at": "2026-07-24T12:42:00+09:00",
      "probs": {
        "1": 0.7548,
        "2": 0.0584,
        "3": 0.0478,
        "4": 0.1166,
        "5": 0.0178,
        "6": 0.0046
      },
      "top_pick": 1,
      "confidence": 0.7548,
      "reason_tags": [
        "全国勝率6.39はレース内1位",
        "当地勝率6.88はレース内1位"
      ]
    },
    {
      "venue": {
        "code": "17",
        "name": "宮島"
      },
      "race_no": 5,
      "close_scheduled_at": "2026-07-24T13:13:00+09:00",
      "probs": {
        "1": 0.2886,
        "2": 0.3643,
        "3": 0.1211,
        "4": 0.1674,
        "5": 0.0557,
        "6": 0.0028
      },
      "top_pick": 2,
      "confidence": 0.3643,
      "reason_tags": [
        "全国勝率6.90はレース内1位"
      ]
    },
    {
      "venue": {
        "code": "17",
        "name": "宮島"
      },
      "race_no": 6,
      "close_scheduled_at": "2026-07-24T13:42:00+09:00",
      "probs": {
        "1": 0.4073,
        "2": 0.1147,
        "3": 0.0721,
        "4": 0.1726,
        "5": 0.2247,
        "6": 0.0086
      },
      "top_pick": 1,
      "confidence": 0.4073,
      "reason_tags": [
        "1号艇（イン）"
      ]
    },
    {
      "venue": {
        "code": "17",
        "name": "宮島"
      },
      "race_no": 7,
      "close_scheduled_at": "2026-07-24T14:10:00+09:00",
      "probs": {
        "1": 0.5911,
        "2": 0.0329,
        "3": 0.1384,
        "4": 0.2169,
        "5": 0.019,
        "6": 0.0017
      },
      "top_pick": 1,
      "confidence": 0.5911,
      "reason_tags": [
        "1号艇（イン）"
      ]
    },
    {
      "venue": {
        "code": "17",
        "name": "宮島"
      },
      "race_no": 8,
      "close_scheduled_at": "2026-07-24T14:35:00+09:00",
      "probs": {
        "1": 0.6779,
        "2": 0.0964,
        "3": 0.1072,
        "4": 0.0621,
        "5": 0.0483,
        "6": 0.0081
      },
      "top_pick": 1,
      "confidence": 0.6779,
      "reason_tags": [
        "全国勝率5.01はレース内1位",
        "当地勝率4.92はレース内1位"
      ]
    },
    {
      "venue": {
        "code": "17",
        "name": "宮島"
      },
      "race_no": 9,
      "close_scheduled_at": "2026-07-24T15:03:00+09:00",
      "probs": {
        "1": 0.4345,
        "2": 0.1272,
        "3": 0.0994,
        "4": 0.1623,
        "5": 0.0673,
        "6": 0.1093
      },
      "top_pick": 1,
      "confidence": 0.4345,
      "reason_tags": [
        "1号艇（イン）"
      ]
    },
    {
      "venue": {
        "code": "17",
        "name": "宮島"
      },
      "race_no": 10,
      "close_scheduled_at": "2026-07-24T15:42:00+09:00",
      "probs": {
        "1": 0.7668,
        "2": 0.0232,
        "3": 0.0676,
        "4": 0.1007,
        "5": 0.0293,
        "6": 0.0124
      },
      "top_pick": 1,
      "confidence": 0.7668,
      "reason_tags": [
        "全国勝率6.24はレース内1位",
        "1号艇（イン）"
      ]
    },
    {
      "venue": {
        "code": "17",
        "name": "宮島"
      },
      "race_no": 11,
      "close_scheduled_at": "2026-07-24T16:15:00+09:00",
      "probs": {
        "1": 0.7691,
        "2": 0.077,
        "3": 0.0453,
        "4": 0.0422,
        "5": 0.0375,
        "6": 0.0289
      },
      "top_pick": 1,
      "confidence": 0.7691,
      "reason_tags": [
        "全国勝率6.28はレース内1位",
        "モーター2連率41%はレース内1位"
      ]
    },
    {
      "venue": {
        "code": "17",
        "name": "宮島"
      },
      "race_no": 12,
      "close_scheduled_at": "2026-07-24T16:50:00+09:00",
      "probs": {
        "1": 0.6011,
        "2": 0.1469,
        "3": 0.0905,
        "4": 0.0994,
        "5": 0.042,
        "6": 0.0201
      },
      "top_pick": 1,
      "confidence": 0.6011,
      "reason_tags": [
        "全国勝率6.92はレース内1位",
        "1号艇（イン）"
      ]
    },
    {
      "venue": {
        "code": "19",
        "name": "下関"
      },
      "race_no": 1,
      "close_scheduled_at": "2026-07-24T15:30:00+09:00",
      "probs": {
        "1": 0.4698,
        "2": 0.2765,
        "3": 0.1405,
        "4": 0.0554,
        "5": 0.0352,
        "6": 0.0227
      },
      "top_pick": 1,
      "confidence": 0.4698,
      "reason_tags": [
        "当地勝率4.43はレース内1位",
        "1号艇（イン）"
      ]
    },
    {
      "venue": {
        "code": "19",
        "name": "下関"
      },
      "race_no": 2,
      "close_scheduled_at": "2026-07-24T16:05:00+09:00",
      "probs": {
        "1": 0.5321,
        "2": 0.3343,
        "3": 0.047,
        "4": 0.0334,
        "5": 0.0097,
        "6": 0.0435
      },
      "top_pick": 1,
      "confidence": 0.5321,
      "reason_tags": [
        "当地勝率6.33はレース内1位",
        "1号艇（イン）"
      ]
    },
    {
      "venue": {
        "code": "19",
        "name": "下関"
      },
      "race_no": 3,
      "close_scheduled_at": "2026-07-24T16:39:00+09:00",
      "probs": {
        "1": 0.4682,
        "2": 0.1154,
        "3": 0.1038,
        "4": 0.1072,
        "5": 0.0934,
        "6": 0.112
      },
      "top_pick": 1,
      "confidence": 0.4682,
      "reason_tags": [
        "1号艇（イン）"
      ]
    },
    {
      "venue": {
        "code": "19",
        "name": "下関"
      },
      "race_no": 4,
      "close_scheduled_at": "2026-07-24T17:13:00+09:00",
      "probs": {
        "1": 0.6508,
        "2": 0.0728,
        "3": 0.1024,
        "4": 0.1016,
        "5": 0.0558,
        "6": 0.0166
      },
      "top_pick": 1,
      "confidence": 0.6508,
      "reason_tags": [
        "当地勝率6.53はレース内1位",
        "モーター2連率56%はレース内1位"
      ]
    },
    {
      "venue": {
        "code": "19",
        "name": "下関"
      },
      "race_no": 5,
      "close_scheduled_at": "2026-07-24T17:37:00+09:00",
      "probs": {
        "1": 0.8738,
        "2": 0.0501,
        "3": 0.0256,
        "4": 0.0248,
        "5": 0.0145,
        "6": 0.0112
      },
      "top_pick": 1,
      "confidence": 0.8738,
      "reason_tags": [
        "全国勝率6.64はレース内1位",
        "当地勝率6.54はレース内1位"
      ]
    },
    {
      "venue": {
        "code": "19",
        "name": "下関"
      },
      "race_no": 6,
      "close_scheduled_at": "2026-07-24T18:04:00+09:00",
      "probs": {
        "1": 0.6624,
        "2": 0.0359,
        "3": 0.042,
        "4": 0.1769,
        "5": 0.0705,
        "6": 0.0122
      },
      "top_pick": 1,
      "confidence": 0.6624,
      "reason_tags": [
        "全国勝率6.10はレース内1位",
        "1号艇（イン）"
      ]
    },
    {
      "venue": {
        "code": "19",
        "name": "下関"
      },
      "race_no": 7,
      "close_scheduled_at": "2026-07-24T18:28:00+09:00",
      "probs": {
        "1": 0.8204,
        "2": 0.0445,
        "3": 0.0746,
        "4": 0.0133,
        "5": 0.0151,
        "6": 0.0322
      },
      "top_pick": 1,
      "confidence": 0.8204,
      "reason_tags": [
        "全国勝率5.87はレース内1位",
        "1号艇（イン）"
      ]
    },
    {
      "venue": {
        "code": "19",
        "name": "下関"
      },
      "race_no": 8,
      "close_scheduled_at": "2026-07-24T18:54:00+09:00",
      "probs": {
        "1": 0.8287,
        "2": 0.0348,
        "3": 0.0627,
        "4": 0.0591,
        "5": 0.0089,
        "6": 0.0058
      },
      "top_pick": 1,
      "confidence": 0.8287,
      "reason_tags": [
        "全国勝率5.81はレース内1位",
        "1号艇（イン）"
      ]
    },
    {
      "venue": {
        "code": "19",
        "name": "下関"
      },
      "race_no": 9,
      "close_scheduled_at": "2026-07-24T19:23:00+09:00",
      "probs": {
        "1": 0.5452,
        "2": 0.2297,
        "3": 0.0535,
        "4": 0.0536,
        "5": 0.0261,
        "6": 0.092
      },
      "top_pick": 1,
      "confidence": 0.5452,
      "reason_tags": [
        "モーター2連率42%はレース内1位",
        "1号艇（イン）"
      ]
    },
    {
      "venue": {
        "code": "19",
        "name": "下関"
      },
      "race_no": 10,
      "close_scheduled_at": "2026-07-24T19:50:00+09:00",
      "probs": {
        "1": 0.6858,
        "2": 0.0629,
        "3": 0.1815,
        "4": 0.0164,
        "5": 0.0337,
        "6": 0.0197
      },
      "top_pick": 1,
      "confidence": 0.6858,
      "reason_tags": [
        "1号艇（イン）"
      ]
    },
    {
      "venue": {
        "code": "19",
        "name": "下関"
      },
      "race_no": 11,
      "close_scheduled_at": "2026-07-24T20:16:00+09:00",
      "probs": {
        "1": 0.7212,
        "2": 0.145,
        "3": 0.0513,
        "4": 0.022,
        "5": 0.0536,
        "6": 0.0069
      },
      "top_pick": 1,
      "confidence": 0.7212,
      "reason_tags": [
        "当地勝率7.08はレース内1位",
        "レース内で唯一のA1級"
      ]
    },
    {
      "venue": {
        "code": "19",
        "name": "下関"
      },
      "race_no": 12,
      "close_scheduled_at": "2026-07-24T20:45:00+09:00",
      "probs": {
        "1": 0.399,
        "2": 0.2167,
        "3": 0.1587,
        "4": 0.132,
        "5": 0.0622,
        "6": 0.0314
      },
      "top_pick": 1,
      "confidence": 0.399,
      "reason_tags": [
        "1号艇（イン）"
      ]
    },
    {
      "venue": {
        "code": "21",
        "name": "芦屋"
      },
      "race_no": 1,
      "close_scheduled_at": "2026-07-24T08:32:00+09:00",
      "probs": {
        "1": 0.7249,
        "2": 0.1117,
        "3": 0.0689,
        "4": 0.0422,
        "5": 0.0259,
        "6": 0.0264
      },
      "top_pick": 1,
      "confidence": 0.7249,
      "reason_tags": [
        "全国勝率5.86はレース内1位",
        "当地勝率5.95はレース内1位"
      ]
    },
    {
      "venue": {
        "code": "21",
        "name": "芦屋"
      },
      "race_no": 2,
      "close_scheduled_at": "2026-07-24T08:58:00+09:00",
      "probs": {
        "1": 0.6311,
        "2": 0.0544,
        "3": 0.0482,
        "4": 0.2314,
        "5": 0.029,
        "6": 0.0058
      },
      "top_pick": 1,
      "confidence": 0.6311,
      "reason_tags": [
        "1号艇（イン）"
      ]
    },
    {
      "venue": {
        "code": "21",
        "name": "芦屋"
      },
      "race_no": 3,
      "close_scheduled_at": "2026-07-24T09:24:00+09:00",
      "probs": {
        "1": 0.548,
        "2": 0.0483,
        "3": 0.1899,
        "4": 0.1017,
        "5": 0.1082,
        "6": 0.0039
      },
      "top_pick": 1,
      "confidence": 0.548,
      "reason_tags": [
        "1号艇（イン）"
      ]
    },
    {
      "venue": {
        "code": "21",
        "name": "芦屋"
      },
      "race_no": 4,
      "close_scheduled_at": "2026-07-24T09:50:00+09:00",
      "probs": {
        "1": 0.822,
        "2": 0.0692,
        "3": 0.0182,
        "4": 0.0492,
        "5": 0.0093,
        "6": 0.0321
      },
      "top_pick": 1,
      "confidence": 0.822,
      "reason_tags": [
        "全国勝率6.38はレース内1位",
        "当地勝率7.25はレース内1位"
      ]
    },
    {
      "venue": {
        "code": "21",
        "name": "芦屋"
      },
      "race_no": 5,
      "close_scheduled_at": "2026-07-24T10:16:00+09:00",
      "probs": {
        "1": 0.7502,
        "2": 0.0845,
        "3": 0.0583,
        "4": 0.0652,
        "5": 0.0056,
        "6": 0.0362
      },
      "top_pick": 1,
      "confidence": 0.7502,
      "reason_tags": [
        "レース内で唯一のA1級",
        "1号艇（イン）"
      ]
    },
    {
      "venue": {
        "code": "21",
        "name": "芦屋"
      },
      "race_no": 6,
      "close_scheduled_at": "2026-07-24T10:44:00+09:00",
      "probs": {
        "1": 0.4292,
        "2": 0.1232,
        "3": 0.2884,
        "4": 0.0569,
        "5": 0.0887,
        "6": 0.0136
      },
      "top_pick": 1,
      "confidence": 0.4292,
      "reason_tags": [
        "当地勝率5.92はレース内1位",
        "1号艇（イン）"
      ]
    },
    {
      "venue": {
        "code": "21",
        "name": "芦屋"
      },
      "race_no": 7,
      "close_scheduled_at": "2026-07-24T11:12:00+09:00",
      "probs": {
        "1": 0.6806,
        "2": 0.0805,
        "3": 0.0761,
        "4": 0.0616,
        "5": 0.0555,
        "6": 0.0458
      },
      "top_pick": 1,
      "confidence": 0.6806,
      "reason_tags": [
        "当地勝率6.06はレース内1位",
        "モーター2連率52%はレース内1位"
      ]
    },
    {
      "venue": {
        "code": "21",
        "name": "芦屋"
      },
      "race_no": 8,
      "close_scheduled_at": "2026-07-24T11:43:00+09:00",
      "probs": {
        "1": 0.3325,
        "2": 0.0337,
        "3": 0.0871,
        "4": 0.3851,
        "5": 0.0283,
        "6": 0.1332
      },
      "top_pick": 4,
      "confidence": 0.3851,
      "reason_tags": []
    },
    {
      "venue": {
        "code": "21",
        "name": "芦屋"
      },
      "race_no": 9,
      "close_scheduled_at": "2026-07-24T12:16:00+09:00",
      "probs": {
        "1": 0.654,
        "2": 0.2205,
        "3": 0.0182,
        "4": 0.0505,
        "5": 0.0207,
        "6": 0.0361
      },
      "top_pick": 1,
      "confidence": 0.654,
      "reason_tags": [
        "1号艇（イン）"
      ]
    },
    {
      "venue": {
        "code": "21",
        "name": "芦屋"
      },
      "race_no": 10,
      "close_scheduled_at": "2026-07-24T12:49:00+09:00",
      "probs": {
        "1": 0.2781,
        "2": 0.2121,
        "3": 0.1415,
        "4": 0.0621,
        "5": 0.2197,
        "6": 0.0866
      },
      "top_pick": 1,
      "confidence": 0.2781,
      "reason_tags": [
        "1号艇（イン）"
      ]
    },
    {
      "venue": {
        "code": "21",
        "name": "芦屋"
      },
      "race_no": 11,
      "close_scheduled_at": "2026-07-24T13:23:00+09:00",
      "probs": {
        "1": 0.5272,
        "2": 0.1749,
        "3": 0.0934,
        "4": 0.1094,
        "5": 0.0404,
        "6": 0.0548
      },
      "top_pick": 1,
      "confidence": 0.5272,
      "reason_tags": [
        "1号艇（イン）"
      ]
    },
    {
      "venue": {
        "code": "21",
        "name": "芦屋"
      },
      "race_no": 12,
      "close_scheduled_at": "2026-07-24T14:00:00+09:00",
      "probs": {
        "1": 0.8254,
        "2": 0.0226,
        "3": 0.0822,
        "4": 0.0309,
        "5": 0.0303,
        "6": 0.0087
      },
      "top_pick": 1,
      "confidence": 0.8254,
      "reason_tags": [
        "全国勝率7.03はレース内1位",
        "モーター2連率39%はレース内1位"
      ]
    },
    {
      "venue": {
        "code": "22",
        "name": "福岡"
      },
      "race_no": 1,
      "close_scheduled_at": "2026-07-24T12:18:00+09:00",
      "probs": {
        "1": 0.6063,
        "2": 0.0756,
        "3": 0.0719,
        "4": 0.1571,
        "5": 0.0481,
        "6": 0.0411
      },
      "top_pick": 1,
      "confidence": 0.6063,
      "reason_tags": [
        "1号艇（イン）"
      ]
    },
    {
      "venue": {
        "code": "22",
        "name": "福岡"
      },
      "race_no": 2,
      "close_scheduled_at": "2026-07-24T12:47:00+09:00",
      "probs": {
        "1": 0.7178,
        "2": 0.0549,
        "3": 0.1363,
        "4": 0.0307,
        "5": 0.0345,
        "6": 0.0258
      },
      "top_pick": 1,
      "confidence": 0.7178,
      "reason_tags": [
        "全国勝率7.38はレース内1位",
        "1号艇（イン）"
      ]
    },
    {
      "venue": {
        "code": "22",
        "name": "福岡"
      },
      "race_no": 3,
      "close_scheduled_at": "2026-07-24T13:17:00+09:00",
      "probs": {
        "1": 0.6213,
        "2": 0.1318,
        "3": 0.0985,
        "4": 0.0682,
        "5": 0.0717,
        "6": 0.0086
      },
      "top_pick": 1,
      "confidence": 0.6213,
      "reason_tags": [
        "1号艇（イン）"
      ]
    },
    {
      "venue": {
        "code": "22",
        "name": "福岡"
      },
      "race_no": 4,
      "close_scheduled_at": "2026-07-24T13:49:00+09:00",
      "probs": {
        "1": 0.6557,
        "2": 0.0949,
        "3": 0.0768,
        "4": 0.0565,
        "5": 0.0941,
        "6": 0.0221
      },
      "top_pick": 1,
      "confidence": 0.6557,
      "reason_tags": [
        "1号艇（イン）"
      ]
    },
    {
      "venue": {
        "code": "22",
        "name": "福岡"
      },
      "race_no": 5,
      "close_scheduled_at": "2026-07-24T14:18:00+09:00",
      "probs": {
        "1": 0.2477,
        "2": 0.0815,
        "3": 0.4501,
        "4": 0.0536,
        "5": 0.1289,
        "6": 0.0382
      },
      "top_pick": 3,
      "confidence": 0.4501,
      "reason_tags": [
        "全国勝率7.26はレース内1位",
        "モーター2連率51%はレース内1位"
      ]
    },
    {
      "venue": {
        "code": "22",
        "name": "福岡"
      },
      "race_no": 6,
      "close_scheduled_at": "2026-07-24T14:45:00+09:00",
      "probs": {
        "1": 0.7662,
        "2": 0.1199,
        "3": 0.0509,
        "4": 0.0242,
        "5": 0.0251,
        "6": 0.0138
      },
      "top_pick": 1,
      "confidence": 0.7662,
      "reason_tags": [
        "全国勝率6.61はレース内1位",
        "当地勝率6.48はレース内1位"
      ]
    },
    {
      "venue": {
        "code": "22",
        "name": "福岡"
      },
      "race_no": 7,
      "close_scheduled_at": "2026-07-24T15:14:00+09:00",
      "probs": {
        "1": 0.6004,
        "2": 0.0489,
        "3": 0.1542,
        "4": 0.1126,
        "5": 0.0537,
        "6": 0.0303
      },
      "top_pick": 1,
      "confidence": 0.6004,
      "reason_tags": [
        "当地勝率6.84はレース内1位",
        "1号艇（イン）"
      ]
    },
    {
      "venue": {
        "code": "22",
        "name": "福岡"
      },
      "race_no": 8,
      "close_scheduled_at": "2026-07-24T15:44:00+09:00",
      "probs": {
        "1": 0.6228,
        "2": 0.1053,
        "3": 0.0911,
        "4": 0.0489,
        "5": 0.089,
        "6": 0.0429
      },
      "top_pick": 1,
      "confidence": 0.6228,
      "reason_tags": [
        "1号艇（イン）"
      ]
    },
    {
      "venue": {
        "code": "22",
        "name": "福岡"
      },
      "race_no": 9,
      "close_scheduled_at": "2026-07-24T16:18:00+09:00",
      "probs": {
        "1": 0.7904,
        "2": 0.072,
        "3": 0.0633,
        "4": 0.0279,
        "5": 0.0184,
        "6": 0.0279
      },
      "top_pick": 1,
      "confidence": 0.7904,
      "reason_tags": [
        "全国勝率7.14はレース内1位",
        "当地勝率7.02はレース内1位"
      ]
    },
    {
      "venue": {
        "code": "22",
        "name": "福岡"
      },
      "race_no": 10,
      "close_scheduled_at": "2026-07-24T16:55:00+09:00",
      "probs": {
        "1": 0.5831,
        "2": 0.1324,
        "3": 0.1826,
        "4": 0.072,
        "5": 0.0178,
        "6": 0.012
      },
      "top_pick": 1,
      "confidence": 0.5831,
      "reason_tags": [
        "1号艇（イン）"
      ]
    },
    {
      "venue": {
        "code": "22",
        "name": "福岡"
      },
      "race_no": 11,
      "close_scheduled_at": "2026-07-24T17:22:00+09:00",
      "probs": {
        "1": 0.7723,
        "2": 0.073,
        "3": 0.0645,
        "4": 0.0637,
        "5": 0.0107,
        "6": 0.0159
      },
      "top_pick": 1,
      "confidence": 0.7723,
      "reason_tags": [
        "全国勝率7.41はレース内1位",
        "1号艇（イン）"
      ]
    },
    {
      "venue": {
        "code": "22",
        "name": "福岡"
      },
      "race_no": 12,
      "close_scheduled_at": "2026-07-24T18:00:00+09:00",
      "probs": {
        "1": 0.6599,
        "2": 0.0208,
        "3": 0.1617,
        "4": 0.0294,
        "5": 0.1205,
        "6": 0.0076
      },
      "top_pick": 1,
      "confidence": 0.6599,
      "reason_tags": [
        "1号艇（イン）"
      ]
    },
    {
      "venue": {
        "code": "23",
        "name": "唐津"
      },
      "race_no": 1,
      "close_scheduled_at": "2026-07-24T08:39:00+09:00",
      "probs": {
        "1": 0.8303,
        "2": 0.0691,
        "3": 0.0242,
        "4": 0.0461,
        "5": 0.019,
        "6": 0.0113
      },
      "top_pick": 1,
      "confidence": 0.8303,
      "reason_tags": [
        "全国勝率6.38はレース内1位",
        "当地勝率5.00はレース内1位"
      ]
    },
    {
      "venue": {
        "code": "23",
        "name": "唐津"
      },
      "race_no": 2,
      "close_scheduled_at": "2026-07-24T09:05:00+09:00",
      "probs": {
        "1": 0.627,
        "2": 0.2164,
        "3": 0.0597,
        "4": 0.0582,
        "5": 0.0348,
        "6": 0.0039
      },
      "top_pick": 1,
      "confidence": 0.627,
      "reason_tags": [
        "当地勝率5.38はレース内1位",
        "1号艇（イン）"
      ]
    },
    {
      "venue": {
        "code": "23",
        "name": "唐津"
      },
      "race_no": 3,
      "close_scheduled_at": "2026-07-24T09:31:00+09:00",
      "probs": {
        "1": 0.7792,
        "2": 0.0387,
        "3": 0.0246,
        "4": 0.1393,
        "5": 0.0083,
        "6": 0.0098
      },
      "top_pick": 1,
      "confidence": 0.7792,
      "reason_tags": [
        "当地勝率7.08はレース内1位",
        "1号艇（イン）"
      ]
    },
    {
      "venue": {
        "code": "23",
        "name": "唐津"
      },
      "race_no": 4,
      "close_scheduled_at": "2026-07-24T09:57:00+09:00",
      "probs": {
        "1": 0.4169,
        "2": 0.1697,
        "3": 0.0724,
        "4": 0.2877,
        "5": 0.026,
        "6": 0.0273
      },
      "top_pick": 1,
      "confidence": 0.4169,
      "reason_tags": [
        "モーター2連率46%はレース内1位",
        "1号艇（イン）"
      ]
    },
    {
      "venue": {
        "code": "23",
        "name": "唐津"
      },
      "race_no": 5,
      "close_scheduled_at": "2026-07-24T10:23:00+09:00",
      "probs": {
        "1": 0.7036,
        "2": 0.0283,
        "3": 0.0992,
        "4": 0.1472,
        "5": 0.0114,
        "6": 0.0102
      },
      "top_pick": 1,
      "confidence": 0.7036,
      "reason_tags": [
        "1号艇（イン）"
      ]
    },
    {
      "venue": {
        "code": "23",
        "name": "唐津"
      },
      "race_no": 6,
      "close_scheduled_at": "2026-07-24T10:52:00+09:00",
      "probs": {
        "1": 0.3119,
        "2": 0.3563,
        "3": 0.1323,
        "4": 0.1069,
        "5": 0.021,
        "6": 0.0715
      },
      "top_pick": 2,
      "confidence": 0.3563,
      "reason_tags": [
        "モーター2連率38%はレース内1位"
      ]
    },
    {
      "venue": {
        "code": "23",
        "name": "唐津"
      },
      "race_no": 7,
      "close_scheduled_at": "2026-07-24T11:21:00+09:00",
      "probs": {
        "1": 0.3382,
        "2": 0.4727,
        "3": 0.0756,
        "4": 0.1019,
        "5": 0.0089,
        "6": 0.0027
      },
      "top_pick": 2,
      "confidence": 0.4727,
      "reason_tags": [
        "全国勝率7.39はレース内1位",
        "当地勝率7.11はレース内1位"
      ]
    },
    {
      "venue": {
        "code": "23",
        "name": "唐津"
      },
      "race_no": 8,
      "close_scheduled_at": "2026-07-24T11:50:00+09:00",
      "probs": {
        "1": 0.3019,
        "2": 0.1426,
        "3": 0.1496,
        "4": 0.3563,
        "5": 0.0324,
        "6": 0.0172
      },
      "top_pick": 4,
      "confidence": 0.3563,
      "reason_tags": [
        "全国勝率7.02はレース内1位",
        "レース内で唯一のA1級"
      ]
    },
    {
      "venue": {
        "code": "23",
        "name": "唐津"
      },
      "race_no": 9,
      "close_scheduled_at": "2026-07-24T12:24:00+09:00",
      "probs": {
        "1": 0.663,
        "2": 0.0598,
        "3": 0.1343,
        "4": 0.0478,
        "5": 0.0924,
        "6": 0.0028
      },
      "top_pick": 1,
      "confidence": 0.663,
      "reason_tags": [
        "1号艇（イン）"
      ]
    },
    {
      "venue": {
        "code": "23",
        "name": "唐津"
      },
      "race_no": 10,
      "close_scheduled_at": "2026-07-24T12:56:00+09:00",
      "probs": {
        "1": 0.8352,
        "2": 0.0227,
        "3": 0.0241,
        "4": 0.0844,
        "5": 0.0287,
        "6": 0.0049
      },
      "top_pick": 1,
      "confidence": 0.8352,
      "reason_tags": [
        "全国勝率6.97はレース内1位",
        "1号艇（イン）"
      ]
    },
    {
      "venue": {
        "code": "23",
        "name": "唐津"
      },
      "race_no": 11,
      "close_scheduled_at": "2026-07-24T13:32:00+09:00",
      "probs": {
        "1": 0.6556,
        "2": 0.0644,
        "3": 0.0677,
        "4": 0.1691,
        "5": 0.0228,
        "6": 0.0204
      },
      "top_pick": 1,
      "confidence": 0.6556,
      "reason_tags": [
        "1号艇（イン）"
      ]
    },
    {
      "venue": {
        "code": "23",
        "name": "唐津"
      },
      "race_no": 12,
      "close_scheduled_at": "2026-07-24T14:03:00+09:00",
      "probs": {
        "1": 0.7001,
        "2": 0.0452,
        "3": 0.1514,
        "4": 0.0745,
        "5": 0.0195,
        "6": 0.0092
      },
      "top_pick": 1,
      "confidence": 0.7001,
      "reason_tags": [
        "全国勝率7.02はレース内1位",
        "1号艇（イン）"
      ]
    },
    {
      "venue": {
        "code": "24",
        "name": "大村"
      },
      "race_no": 1,
      "close_scheduled_at": "2026-07-24T17:41:00+09:00",
      "probs": {
        "1": 0.6187,
        "2": 0.0743,
        "3": 0.0895,
        "4": 0.1308,
        "5": 0.0362,
        "6": 0.0506
      },
      "top_pick": 1,
      "confidence": 0.6187,
      "reason_tags": [
        "1号艇（イン）"
      ]
    },
    {
      "venue": {
        "code": "24",
        "name": "大村"
      },
      "race_no": 2,
      "close_scheduled_at": "2026-07-24T18:08:00+09:00",
      "probs": {
        "1": 0.7514,
        "2": 0.0255,
        "3": 0.0843,
        "4": 0.0806,
        "5": 0.0444,
        "6": 0.0138
      },
      "top_pick": 1,
      "confidence": 0.7514,
      "reason_tags": [
        "当地勝率6.64はレース内1位",
        "モーター2連率57%はレース内1位"
      ]
    },
    {
      "venue": {
        "code": "24",
        "name": "大村"
      },
      "race_no": 3,
      "close_scheduled_at": "2026-07-24T18:34:00+09:00",
      "probs": {
        "1": 0.485,
        "2": 0.267,
        "3": 0.0537,
        "4": 0.0413,
        "5": 0.1246,
        "6": 0.0284
      },
      "top_pick": 1,
      "confidence": 0.485,
      "reason_tags": [
        "1号艇（イン）"
      ]
    },
    {
      "venue": {
        "code": "24",
        "name": "大村"
      },
      "race_no": 4,
      "close_scheduled_at": "2026-07-24T19:03:00+09:00",
      "probs": {
        "1": 0.6998,
        "2": 0.1418,
        "3": 0.0583,
        "4": 0.0209,
        "5": 0.0653,
        "6": 0.0139
      },
      "top_pick": 1,
      "confidence": 0.6998,
      "reason_tags": [
        "全国勝率6.00はレース内1位",
        "当地勝率6.52はレース内1位"
      ]
    },
    {
      "venue": {
        "code": "24",
        "name": "大村"
      },
      "race_no": 5,
      "close_scheduled_at": "2026-07-24T19:30:00+09:00",
      "probs": {
        "1": 0.704,
        "2": 0.0941,
        "3": 0.0669,
        "4": 0.0203,
        "5": 0.1129,
        "6": 0.0018
      },
      "top_pick": 1,
      "confidence": 0.704,
      "reason_tags": [
        "1号艇（イン）"
      ]
    },
    {
      "venue": {
        "code": "24",
        "name": "大村"
      },
      "race_no": 6,
      "close_scheduled_at": "2026-07-24T19:56:00+09:00",
      "probs": {
        "1": 0.8321,
        "2": 0.0316,
        "3": 0.0398,
        "4": 0.0205,
        "5": 0.0166,
        "6": 0.0594
      },
      "top_pick": 1,
      "confidence": 0.8321,
      "reason_tags": [
        "全国勝率7.20はレース内1位",
        "モーター2連率37%はレース内1位"
      ]
    },
    {
      "venue": {
        "code": "24",
        "name": "大村"
      },
      "race_no": 7,
      "close_scheduled_at": "2026-07-24T20:25:00+09:00",
      "probs": {
        "1": 0.6299,
        "2": 0.0855,
        "3": 0.1134,
        "4": 0.0391,
        "5": 0.1188,
        "6": 0.0134
      },
      "top_pick": 1,
      "confidence": 0.6299,
      "reason_tags": [
        "1号艇（イン）"
      ]
    },
    {
      "venue": {
        "code": "24",
        "name": "大村"
      },
      "race_no": 8,
      "close_scheduled_at": "2026-07-24T20:59:00+09:00",
      "probs": {
        "1": 0.5746,
        "2": 0.0541,
        "3": 0.3158,
        "4": 0.0277,
        "5": 0.0085,
        "6": 0.0193
      },
      "top_pick": 1,
      "confidence": 0.5746,
      "reason_tags": [
        "1号艇（イン）"
      ]
    },
    {
      "venue": {
        "code": "24",
        "name": "大村"
      },
      "race_no": 9,
      "close_scheduled_at": "2026-07-24T21:25:00+09:00",
      "probs": {
        "1": 0.6321,
        "2": 0.127,
        "3": 0.1068,
        "4": 0.0845,
        "5": 0.0247,
        "6": 0.0249
      },
      "top_pick": 1,
      "confidence": 0.6321,
      "reason_tags": [
        "全国勝率6.19はレース内1位",
        "モーター2連率54%はレース内1位"
      ]
    },
    {
      "venue": {
        "code": "24",
        "name": "大村"
      },
      "race_no": 10,
      "close_scheduled_at": "2026-07-24T21:51:00+09:00",
      "probs": {
        "1": 0.7073,
        "2": 0.1036,
        "3": 0.0662,
        "4": 0.0861,
        "5": 0.0312,
        "6": 0.0055
      },
      "top_pick": 1,
      "confidence": 0.7073,
      "reason_tags": [
        "当地勝率7.44はレース内1位",
        "1号艇（イン）"
      ]
    },
    {
      "venue": {
        "code": "24",
        "name": "大村"
      },
      "race_no": 11,
      "close_scheduled_at": "2026-07-24T22:16:00+09:00",
      "probs": {
        "1": 0.8076,
        "2": 0.059,
        "3": 0.0653,
        "4": 0.0403,
        "5": 0.0212,
        "6": 0.0066
      },
      "top_pick": 1,
      "confidence": 0.8076,
      "reason_tags": [
        "全国勝率6.89はレース内1位",
        "当地勝率7.75はレース内1位"
      ]
    },
    {
      "venue": {
        "code": "24",
        "name": "大村"
      },
      "race_no": 12,
      "close_scheduled_at": "2026-07-24T22:41:00+09:00",
      "probs": {
        "1": 0.8196,
        "2": 0.0993,
        "3": 0.0229,
        "4": 0.0442,
        "5": 0.0115,
        "6": 0.0025
      },
      "top_pick": 1,
      "confidence": 0.8196,
      "reason_tags": [
        "全国勝率6.87はレース内1位",
        "当地勝率8.69はレース内1位"
      ]
    }
  ],
  "summary": {
    "scheduled": 180,
    "predicted": 180,
    "failed": 0,
    "failed_races": []
  }
}